LICENSE
README.md
pyproject.toml
setup.cfg
setup.py
uranium_quantum.egg-info/PKG-INFO
uranium_quantum.egg-info/SOURCES.txt
uranium_quantum.egg-info/dependency_links.txt
uranium_quantum.egg-info/requires.txt
uranium_quantum.egg-info/top_level.txt
uranium_quantum/circuit_composer/__init__.py
uranium_quantum/circuit_composer/circuit_composer.py
uranium_quantum/circuit_composer/random_circuit_generator.py
uranium_quantum/circuit_exporter/__init__.py
uranium_quantum/circuit_exporter/base-exporter.py
uranium_quantum/circuit_exporter/cirq-exporter.py
uranium_quantum/circuit_exporter/export-circuit.py
uranium_quantum/circuit_exporter/exported_circuit_qiskit.py
uranium_quantum/circuit_exporter/pyquil-exporter.py
uranium_quantum/circuit_exporter/qiskit-exporter.py
uranium_quantum/circuit_exporter/qiskit_custom_gates.py
uranium_quantum/circuit_exporter/quil-exporter.py