Metadata-Version: 2.1
Name: uranium-quantum
Version: 0.3.0
Summary: Support libraries for the Uranium quantum computing platform (https://uranium.transilvania-quantum.org/).
Home-page: https://github.com/radumarg/uranium-quantum
Download-URL: https://github.com/radumarg/uranium-quantum/releases/tag/v0.2.5
Author: Radu Marginean
Author-email: radu.marg@gmail.com
License: MIT
Keywords: quantum,computing,uranium platform
Platform: UNKNOWN
Classifier: Development Status :: 3 - Alpha
Classifier: Intended Audience :: Developers
Classifier: Topic :: Software Development :: Build Tools
Classifier: License :: OSI Approved :: MIT License
Classifier: Programming Language :: Python :: 3
Classifier: Programming Language :: Python :: 3.7
Classifier: Programming Language :: Python :: 3.8
Classifier: Programming Language :: Python :: 3.9
Classifier: Programming Language :: Python :: 3.10
License-File: LICENSE
